cloudtask/__init__.py
cloudtask/apps.py
cloudtask/client.py
cloudtask/configs.py
cloudtask/decorators.py
cloudtask/encoder.py
cloudtask/exceptions.py
cloudtask/tasks.py
cloudtask/urls.py
cloudtask/utils.py
cloudtask/views.py
cloudtask/worker.py
cloudtask/management/__init__.py
cloudtask/management/commands/__init__.py
cloudtask/management/commands/cloudtask-worker.py
dj_cloud_task-0.1.2.dist-info/LICENCE
dj_cloud_task-0.1.2.dist-info/METADATA
dj_cloud_task-0.1.2.dist-info/WHEEL
dj_cloud_task-0.1.2.dist-info/top_level.txt
dj_cloud_task-0.1.2.dist-info/RECORD
