Metadata-Version: 2.1
Name: dj-cloud-task
Version: 0.1.2
Summary: Integrate your django application with Google Cloud Task from Google Cloud Platform
Home-page: https://github.com/txiocoder/dj-cloud-task
Author: AM
Author-email: txiocoder@gmail.com
Maintainer: AM
Maintainer-email: txiocoder@gmail.com
License: MIT-Licence
Project-URL: Documentation, https://github.com/txiocoder/dj-cloud-task
Project-URL: Source, https://github.com/txiocoder/dj-cloud-task
Keywords: django,cloud task,tasks,google cloud,google cloud tasks
Platform: UNKNOWN
Classifier: Environment :: Web Environment
Classifier: Framework :: Django
Classifier: Intended Audience :: Developers
Classifier: License :: OSI Approved :: MIT License
Classifier: Operating System :: OS Independent
Classifier: Programming Language :: Python
Classifier: Programming Language :: Python :: 3
Classifier: Programming Language :: Python :: 3 :: Only
Classifier: Programming Language :: Python :: 3.8
Classifier: Programming Language :: Python :: 3.9
Classifier: Topic :: Internet :: WWW/HTTP
Classifier: Topic :: Software Development :: Libraries :: Application Frameworks
Classifier: Topic :: Software Development :: Libraries :: Python Modules
Requires-Python: >=3.8
License-File: LICENCE
Requires-Dist: google-cloud-tasks (>=2.5.*)
